llama_index/readers/firebase_realtimedb/__init__.py
llama_index/readers/firebase_realtimedb/base.py
llama_index_readers_firebase_realtimedb-0.4.1.dist-info/METADATA
llama_index_readers_firebase_realtimedb-0.4.1.dist-info/WHEEL
llama_index_readers_firebase_realtimedb-0.4.1.dist-info/licenses/LICENSE
llama_index_readers_firebase_realtimedb-0.4.1.dist-info/RECORD
