Metadata-Version: 2.4
Name: llama-index-readers-firebase-realtimedb
Version: 0.4.1
Summary: llama-index readers firebase_realtimedb integration
Author-email: Your Name <you@example.com>
Maintainer: ajay
License-Expression: MIT
License-File: LICENSE
Keywords: database,firebase,realtimedb
Requires-Python: <4.0,>=3.9
Requires-Dist: firebase-admin<7,>=6.4.0
Requires-Dist: llama-index-core<0.15,>=0.13.0
